s3_security_scanner/__init__.py
s3_security_scanner/bucket_utils.py
s3_security_scanner/cli.py
s3_security_scanner/compliance.py
s3_security_scanner/html_reporter.py
s3_security_scanner/scanner.py
s3_security_scanner/utils.py
s3_security_scanner/analyzers/__init__.py
s3_security_scanner/analyzers/dns_analyzer.py
s3_security_scanner/analyzers/pattern_analyzer.py
s3_security_scanner/checks/__init__.py
s3_security_scanner/checks/access_control.py
s3_security_scanner/checks/account_security.py
s3_security_scanner/checks/base.py
s3_security_scanner/checks/cloudtrail_logging.py
s3_security_scanner/checks/dns_security.py
s3_security_scanner/checks/encryption.py
s3_security_scanner/checks/gdpr_compliance.py
s3_security_scanner/checks/iso_compliance.py
s3_security_scanner/checks/logging_monitoring.py
s3_security_scanner/checks/object_security.py
s3_security_scanner/checks/soc2_monitoring.py
s3_security_scanner/checks/threat_detection.py
s3_security_scanner/checks/versioning_lifecycle.py
s3_security_scanner/discovery/__init__.py
s3_security_scanner/discovery/bucket_discovery.py
s3_security_scanner/discovery/dns_validator.py
s3_security_scanner/discovery/http_validator.py
s3_security_scanner/discovery/permutation_generator.py
s3_security_scanner/discovery/s3_bucket_wordlist.txt
s3_security_scanner/discovery/subdomain_wordlist.txt
s3_security_scanner/discovery/wordlist_manager.py
s3_security_scanner/templates/report.html
s3_security_scanner-1.0.1.dist-info/licenses/LICENSE
s3_security_scanner-1.0.1.dist-info/METADATA
s3_security_scanner-1.0.1.dist-info/WHEEL
s3_security_scanner-1.0.1.dist-info/entry_points.txt
s3_security_scanner-1.0.1.dist-info/top_level.txt
s3_security_scanner-1.0.1.dist-info/RECORD
