Metadata-Version: 2.4
Name: s3-security-scanner
Version: 1.0.1
Summary: A comprehensive AWS S3 bucket security scanner with compliance mapping
Author-email: Toc Consulting <tarek@tocconsulting.fr>
License-Expression: MIT
Project-URL: Homepage, https://github.com/TocConsulting/s3-security-scanner
Project-URL: Documentation, https://github.com/TocConsulting/s3-security-scanner#readme
Project-URL: Repository, https://github.com/TocConsulting/s3-security-scanner
Project-URL: Issues, https://github.com/TocConsulting/s3-security-scanner/issues
Keywords: aws,s3,security,compliance,scanner,cloud,audit
Classifier: Development Status :: 5 - Production/Stable
Classifier: Intended Audience :: System Administrators
Classifier: Intended Audience :: Developers
Classifier: Topic :: Security
Classifier: Topic :: System :: Systems Administration
Classifier: Programming Language :: Python :: 3
Classifier: Programming Language :: Python :: 3.8
Classifier: Programming Language :: Python :: 3.9
Classifier: Programming Language :: Python :: 3.10
Classifier: Programming Language :: Python :: 3.11
Classifier: Programming Language :: Python :: 3.12
Classifier: Programming Language :: Python :: 3.13
Classifier: Operating System :: OS Independent
Requires-Python: >=3.8
License-File: LICENSE
Requires-Dist: boto3>=1.26.0
Requires-Dist: botocore>=1.29.0
Requires-Dist: rich>=13.0.0
Requires-Dist: click>=8.1.0
Requires-Dist: jinja2>=3.1.0
Requires-Dist: dnspython>=2.4.0
Requires-Dist: requests>=2.28.0
Requires-Dist: urllib3>=1.26.0
Provides-Extra: async
Requires-Dist: aiodns>=3.0.0; extra == "async"
Provides-Extra: dev
Requires-Dist: pytest>=7.2.0; extra == "dev"
Requires-Dist: pytest-cov>=4.0.0; extra == "dev"
Requires-Dist: black>=23.0.0; extra == "dev"
Requires-Dist: flake8>=6.0.0; extra == "dev"
Requires-Dist: mypy>=1.0.0; extra == "dev"
Requires-Dist: pre-commit>=3.0.0; extra == "dev"
Requires-Dist: moto[s3]>=4.0.0; extra == "dev"
Dynamic: license-file
